texjam/__init__.py
texjam/cli/__init__.py
texjam/cli/app.py
texjam/cli/package.py
texjam/cli/source.py
texjam/config/__init__.py
texjam/config/config.py
texjam/config/meta.py
texjam/exception.py
texjam/render/__init__.py
texjam/render/executor.py
texjam/render/path.py
texjam-0.5.5.dist-info/METADATA
texjam-0.5.5.dist-info/WHEEL
texjam-0.5.5.dist-info/entry_points.txt
texjam-0.5.5.dist-info/licenses/LICENSE
texjam-0.5.5.dist-info/RECORD
