Metadata-Version: 2.4
Name: texjam
Version: 0.5.5
Summary: A tool for managing LaTeX project templates.
License: MIT
License-File: LICENSE
Author: Quaerent
Author-email: topfyf@qq.com
Requires-Python: >=3.12,<4.0
Classifier: Development Status :: 4 - Beta
Classifier: Intended Audience :: Developers
Classifier: Intended Audience :: Science/Research
Classifier: Intended Audience :: Education
Classifier: Topic :: Text Processing
Classifier: Topic :: Text Processing :: Markup
Classifier: Topic :: Text Processing :: Markup :: LaTeX
Classifier: Topic :: Software Development :: Code Generators
Classifier: Topic :: Utilities
Classifier: License :: OSI Approved :: MIT License
Classifier: Programming Language :: Python :: 3
Classifier: Programming Language :: Python :: 3.12
Classifier: Programming Language :: Python :: 3.13
Classifier: Operating System :: OS Independent
Requires-Dist: appdirs (>=1.4.4,<2.0.0)
Requires-Dist: binaryornot (>=0.4.4,<0.5.0)
Requires-Dist: jinja2 (>=3.1.6,<4.0.0)
Requires-Dist: pydantic (>=2.12.5,<3.0.0)
Requires-Dist: pyyaml (>=6.0.3,<7.0.0)
Requires-Dist: questionary (>=2.1.1,<3.0.0)
Requires-Dist: rich (>=14.2.0,<15.0.0)
Requires-Dist: typer (>=0.21.1,<0.22.0)
Project-URL: Homepage, https://github.com/quaerent/texjam
Project-URL: Issues, https://github.com/quaerent/texjam/issues
Project-URL: Repository, https://github.com/quaerent/texjam
